bulk_tracker/__init__.py
bulk_tracker/apps.py
bulk_tracker/collector.py
bulk_tracker/helper_objects.py
bulk_tracker/managers.py
bulk_tracker/models.py
bulk_tracker/signals.py
bulk_tracker/utils.py
tests/__init__.py
tests/models.py
tests/settings.py
tests/test_create_signal.py
tests/test_delete_signal.py
tests/test_update_signal.py
django_bulk_tracker-0.2.1.dist-info/METADATA
django_bulk_tracker-0.2.1.dist-info/WHEEL
django_bulk_tracker-0.2.1.dist-info/top_level.txt
django_bulk_tracker-0.2.1.dist-info/RECORD
